{"nodes": [{"id": "c_users_aoune_webapp_budget_app_src_app_g_tag_page_tsx", "label": "page.tsx", "file_type": "code", "source_file": "C:\\Users\\aoune\\WebApp\\budget-app\\src\\app\\g\\[tag]\\page.tsx", "source_location": "L1"}, {"id": "tag_page_guestportalpage", "label": "GuestPortalPage()", "file_type": "code", "source_file": "C:\\Users\\aoune\\WebApp\\budget-app\\src\\app\\g\\[tag]\\page.tsx", "source_location": "L6"}], "edges": [{"source": "c_users_aoune_webapp_budget_app_src_app_g_tag_page_tsx", "target": "c_users_aoune_webapp_budget_app_src_app_g_tag_guest_portal_client", "relation": "imports_from", "confidence": "EXTRACTED", "source_file": "C:\\Users\\aoune\\WebApp\\budget-app\\src\\app\\g\\[tag]\\page.tsx", "source_location": "L2", "weight": 1.0}, {"source": "c_users_aoune_webapp_budget_app_src_app_g_tag_page_tsx", "target": "tag_page_guestportalpage", "relation": "contains", "confidence": "EXTRACTED", "source_file": "C:\\Users\\aoune\\WebApp\\budget-app\\src\\app\\g\\[tag]\\page.tsx", "source_location": "L6", "weight": 1.0}], "raw_calls": []}